<?xml version="1.0" encoding="UTF-8" ?>
<!DOCTYPE mapper PUBLIC "-//mybatis.org//DTD Mapper 3.0//EN" "http://mybatis.org/dtd/mybatis-3-mapper.dtd" >
<mapper namespace="com.chinasofti.cetp.practice.dao.TaskAnswerMapper" >
  <resultMap id="BaseResultMap" type="com.chinasofti.cetp.practice.model.TaskAnswer" >
    <!--
      WARNING - @mbggenerated
      This element is automatically generated by MyBatis Generator, do not modify.
      This element was generated on Thu Jul 25 19:47:24 CST 2013.
    -->
    <id column="TA_ANSWER_ID" property="taAnswerId" jdbcType="INTEGER" />
    <result column="TA_TASK_ID" property="taTaskId" jdbcType="INTEGER" />
    <result column="TA_ANSWER_NAME" property="taAnswerName" jdbcType="VARCHAR" />
    <result column="TA_ANSWER_URL" property="taAnswerUrl" jdbcType="VARCHAR" />
    <result column="TA_ANSWER_VIDEO_URL" property="taAnswerVideoUrl" jdbcType="VARCHAR" />
    <result column="TA_ANSWER_TYPE" property="taAnswerType" jdbcType="CHAR" />
    <result column="TA_REGTIME" property="taRegtime" jdbcType="TIMESTAMP" />
  </resultMap>
  <sql id="Example_Where_Clause" >
    <!--
      WARNING - @mbggenerated
      This element is automatically generated by MyBatis Generator, do not modify.
      This element was generated on Thu Jul 25 19:47:24 CST 2013.
    -->
    <where >
      <foreach collection="oredCriteria" item="criteria" separator="or" >
        <if test="criteria.valid" >
          <trim prefix="(" suffix=")" prefixOverrides="and" >
            <foreach collection="criteria.criteria" item="criterion" >
              <choose >
                <when test="criterion.noValue" >
                  and ${criterion.condition}
                </when>
                <when test="criterion.singleValue" >
                  and ${criterion.condition} #{criterion.value}
                </when>
                <when test="criterion.betweenValue" >
                  and ${criterion.condition} #{criterion.value} and #{criterion.secondValue}
                </when>
                <when test="criterion.listValue" >
                  and ${criterion.condition}
                  <foreach collection="criterion.value" item="listItem" open="(" close=")" separator="," >
                    #{listItem}
                  </foreach>
                </when>
              </choose>
            </foreach>
          </trim>
        </if>
      </foreach>
    </where>
  </sql>
  <sql id="Update_By_Example_Where_Clause" >
    <!--
      WARNING - @mbggenerated
      This element is automatically generated by MyBatis Generator, do not modify.
      This element was generated on Thu Jul 25 19:47:24 CST 2013.
    -->
    <where >
      <foreach collection="example.oredCriteria" item="criteria" separator="or" >
        <if test="criteria.valid" >
          <trim prefix="(" suffix=")" prefixOverrides="and" >
            <foreach collection="criteria.criteria" item="criterion" >
              <choose >
                <when test="criterion.noValue" >
                  and ${criterion.condition}
                </when>
                <when test="criterion.singleValue" >
                  and ${criterion.condition} #{criterion.value}
                </when>
                <when test="criterion.betweenValue" >
                  and ${criterion.condition} #{criterion.value} and #{criterion.secondValue}
                </when>
                <when test="criterion.listValue" >
                  and ${criterion.condition}
                  <foreach collection="criterion.value" item="listItem" open="(" close=")" separator="," >
                    #{listItem}
                  </foreach>
                </when>
              </choose>
            </foreach>
          </trim>
        </if>
      </foreach>
    </where>
  </sql>
  <sql id="Base_Column_List" >
    <!--
      WARNING - @mbggenerated
      This element is automatically generated by MyBatis Generator, do not modify.
      This element was generated on Thu Jul 25 19:47:24 CST 2013.
    -->
    TA_ANSWER_ID, TA_TASK_ID, TA_ANSWER_NAME, TA_ANSWER_URL, TA_ANSWER_VIDEO_URL, TA_ANSWER_TYPE, 
    TA_REGTIME
  </sql>
  <select id="selectByExample" resultMap="BaseResultMap" parameterType="com.chinasofti.cetp.practice.model.TaskAnswerExample" >
    <!--
      WARNING - @mbggenerated
      This element is automatically generated by MyBatis Generator, do not modify.
      This element was generated on Thu Jul 25 19:47:24 CST 2013.
    -->
    select
    <if test="distinct" >
      distinct
    </if>
    <include refid="Base_Column_List" />
    from tp_task_answer
    <if test="_parameter != null" >
      <include refid="Example_Where_Clause" />
    </if>
    <if test="orderByClause != null" >
      order by ${orderByClause}
    </if>
  </select>
  <select id="selectByPrimaryKey" resultMap="BaseResultMap" parameterType="java.lang.Integer" >
    <!--
      WARNING - @mbggenerated
      This element is automatically generated by MyBatis Generator, do not modify.
      This element was generated on Thu Jul 25 19:47:24 CST 2013.
    -->
    select 
    <include refid="Base_Column_List" />
    from tp_task_answer
    where TA_ANSWER_ID = #{taAnswerId,jdbcType=INTEGER}
  </select>
  <delete id="deleteByPrimaryKey" parameterType="java.lang.Integer" >
    <!--
      WARNING - @mbggenerated
      This element is automatically generated by MyBatis Generator, do not modify.
      This element was generated on Thu Jul 25 19:47:24 CST 2013.
    -->
    delete from tp_task_answer
    where TA_ANSWER_ID = #{taAnswerId,jdbcType=INTEGER}
  </delete>
  <delete id="deleteByExample" parameterType="com.chinasofti.cetp.practice.model.TaskAnswerExample" >
    <!--
      WARNING - @mbggenerated
      This element is automatically generated by MyBatis Generator, do not modify.
      This element was generated on Thu Jul 25 19:47:24 CST 2013.
    -->
    delete from tp_task_answer
    <if test="_parameter != null" >
      <include refid="Example_Where_Clause" />
    </if>
  </delete>
  <insert id="insert" parameterType="com.chinasofti.cetp.practice.model.TaskAnswer" >
    <!--
      WARNING - @mbggenerated
      This element is automatically generated by MyBatis Generator, do not modify.
      This element was generated on Thu Jul 25 19:47:24 CST 2013.
    -->
    insert into tp_task_answer (TA_ANSWER_ID, TA_TASK_ID, TA_ANSWER_NAME, 
      TA_ANSWER_URL, TA_ANSWER_VIDEO_URL, TA_ANSWER_TYPE, 
      TA_REGTIME)
    values (#{taAnswerId,jdbcType=INTEGER}, #{taTaskId,jdbcType=INTEGER}, #{taAnswerName,jdbcType=VARCHAR}, 
      #{taAnswerUrl,jdbcType=VARCHAR}, #{taAnswerVideoUrl,jdbcType=VARCHAR}, #{taAnswerType,jdbcType=CHAR}, 
      #{taRegtime,jdbcType=TIMESTAMP})
  </insert>
  <insert id="insertSelective" parameterType="com.chinasofti.cetp.practice.model.TaskAnswer" >
    <!--
      WARNING - @mbggenerated
      This element is automatically generated by MyBatis Generator, do not modify.
      This element was generated on Thu Jul 25 19:47:24 CST 2013.
    -->
    insert into tp_task_answer
    <trim prefix="(" suffix=")" suffixOverrides="," >
      <if test="taAnswerId != null" >
        TA_ANSWER_ID,
      </if>
      <if test="taTaskId != null" >
        TA_TASK_ID,
      </if>
      <if test="taAnswerName != null" >
        TA_ANSWER_NAME,
      </if>
      <if test="taAnswerUrl != null" >
        TA_ANSWER_URL,
      </if>
      <if test="taAnswerVideoUrl != null" >
        TA_ANSWER_VIDEO_URL,
      </if>
      <if test="taAnswerType != null" >
        TA_ANSWER_TYPE,
      </if>
      <if test="taRegtime != null" >
        TA_REGTIME,
      </if>
    </trim>
    <trim prefix="values (" suffix=")" suffixOverrides="," >
      <if test="taAnswerId != null" >
        #{taAnswerId,jdbcType=INTEGER},
      </if>
      <if test="taTaskId != null" >
        #{taTaskId,jdbcType=INTEGER},
      </if>
      <if test="taAnswerName != null" >
        #{taAnswerName,jdbcType=VARCHAR},
      </if>
      <if test="taAnswerUrl != null" >
        #{taAnswerUrl,jdbcType=VARCHAR},
      </if>
      <if test="taAnswerVideoUrl != null" >
        #{taAnswerVideoUrl,jdbcType=VARCHAR},
      </if>
      <if test="taAnswerType != null" >
        #{taAnswerType,jdbcType=CHAR},
      </if>
      <if test="taRegtime != null" >
        #{taRegtime,jdbcType=TIMESTAMP},
      </if>
    </trim>
  </insert>
  <select id="countByExample" parameterType="com.chinasofti.cetp.practice.model.TaskAnswerExample" resultType="java.lang.Integer" >
    <!--
      WARNING - @mbggenerated
      This element is automatically generated by MyBatis Generator, do not modify.
      This element was generated on Thu Jul 25 19:47:24 CST 2013.
    -->
    select count(*) from tp_task_answer
    <if test="_parameter != null" >
      <include refid="Example_Where_Clause" />
    </if>
  </select>
  <update id="updateByExampleSelective" parameterType="map" >
    <!--
      WARNING - @mbggenerated
      This element is automatically generated by MyBatis Generator, do not modify.
      This element was generated on Thu Jul 25 19:47:24 CST 2013.
    -->
    update tp_task_answer
    <set >
      <if test="record.taAnswerId != null" >
        TA_ANSWER_ID = #{record.taAnswerId,jdbcType=INTEGER},
      </if>
      <if test="record.taTaskId != null" >
        TA_TASK_ID = #{record.taTaskId,jdbcType=INTEGER},
      </if>
      <if test="record.taAnswerName != null" >
        TA_ANSWER_NAME = #{record.taAnswerName,jdbcType=VARCHAR},
      </if>
      <if test="record.taAnswerUrl != null" >
        TA_ANSWER_URL = #{record.taAnswerUrl,jdbcType=VARCHAR},
      </if>
      <if test="record.taAnswerVideoUrl != null" >
        TA_ANSWER_VIDEO_URL = #{record.taAnswerVideoUrl,jdbcType=VARCHAR},
      </if>
      <if test="record.taAnswerType != null" >
        TA_ANSWER_TYPE = #{record.taAnswerType,jdbcType=CHAR},
      </if>
      <if test="record.taRegtime != null" >
        TA_REGTIME = #{record.taRegtime,jdbcType=TIMESTAMP},
      </if>
    </set>
    <if test="_parameter != null" >
      <include refid="Update_By_Example_Where_Clause" />
    </if>
  </update>
  <update id="updateByExample" parameterType="map" >
    <!--
      WARNING - @mbggenerated
      This element is automatically generated by MyBatis Generator, do not modify.
      This element was generated on Thu Jul 25 19:47:24 CST 2013.
    -->
    update tp_task_answer
    set TA_ANSWER_ID = #{record.taAnswerId,jdbcType=INTEGER},
      TA_TASK_ID = #{record.taTaskId,jdbcType=INTEGER},
      TA_ANSWER_NAME = #{record.taAnswerName,jdbcType=VARCHAR},
      TA_ANSWER_URL = #{record.taAnswerUrl,jdbcType=VARCHAR},
      TA_ANSWER_VIDEO_URL = #{record.taAnswerVideoUrl,jdbcType=VARCHAR},
      TA_ANSWER_TYPE = #{record.taAnswerType,jdbcType=CHAR},
      TA_REGTIME = #{record.taRegtime,jdbcType=TIMESTAMP}
    <if test="_parameter != null" >
      <include refid="Update_By_Example_Where_Clause" />
    </if>
  </update>
  <update id="updateByPrimaryKeySelective" parameterType="com.chinasofti.cetp.practice.model.TaskAnswer" >
    <!--
      WARNING - @mbggenerated
      This element is automatically generated by MyBatis Generator, do not modify.
      This element was generated on Thu Jul 25 19:47:24 CST 2013.
    -->
    update tp_task_answer
    <set >
      <if test="taTaskId != null" >
        TA_TASK_ID = #{taTaskId,jdbcType=INTEGER},
      </if>
      <if test="taAnswerName != null" >
        TA_ANSWER_NAME = #{taAnswerName,jdbcType=VARCHAR},
      </if>
      <if test="taAnswerUrl != null" >
        TA_ANSWER_URL = #{taAnswerUrl,jdbcType=VARCHAR},
      </if>
      <if test="taAnswerVideoUrl != null" >
        TA_ANSWER_VIDEO_URL = #{taAnswerVideoUrl,jdbcType=VARCHAR},
      </if>
      <if test="taAnswerType != null" >
        TA_ANSWER_TYPE = #{taAnswerType,jdbcType=CHAR},
      </if>
      <if test="taRegtime != null" >
        TA_REGTIME = #{taRegtime,jdbcType=TIMESTAMP},
      </if>
    </set>
    where TA_ANSWER_ID = #{taAnswerId,jdbcType=INTEGER}
  </update>
  <update id="updateByPrimaryKey" parameterType="com.chinasofti.cetp.practice.model.TaskAnswer" >
    <!--
      WARNING - @mbggenerated
      This element is automatically generated by MyBatis Generator, do not modify.
      This element was generated on Thu Jul 25 19:47:24 CST 2013.
    -->
    update tp_task_answer
    set TA_TASK_ID = #{taTaskId,jdbcType=INTEGER},
      TA_ANSWER_NAME = #{taAnswerName,jdbcType=VARCHAR},
      TA_ANSWER_URL = #{taAnswerUrl,jdbcType=VARCHAR},
      TA_ANSWER_VIDEO_URL = #{taAnswerVideoUrl,jdbcType=VARCHAR},
      TA_ANSWER_TYPE = #{taAnswerType,jdbcType=CHAR},
      TA_REGTIME = #{taRegtime,jdbcType=TIMESTAMP}
    where TA_ANSWER_ID = #{taAnswerId,jdbcType=INTEGER}
  </update>
</mapper>